psremoter/__init__.py
psremoter/connector.py
psremoter-1.0.4.dist-info/LICENSE.txt
psremoter-1.0.4.dist-info/METADATA
psremoter-1.0.4.dist-info/WHEEL
psremoter-1.0.4.dist-info/top_level.txt
psremoter-1.0.4.dist-info/RECORD
