Metadata-Version: 2.1
Name: psremoter
Version: 1.0.4
Summary: Powershell remote client tool for Python
Home-page: https://github.com/danielMandelblat/psremoter
Author: Daniel Mandelblat
Author-email: danielmande@gmail.cm
Project-URL: Bug Tracker, https://github.com/danielMandelblat/psremoter
Classifier: Programming Language :: Python :: 3
Classifier: License :: OSI Approved :: MIT License
Classifier: Operating System :: OS Independent
Requires-Python: >=3.9
License-File: LICENSE.txt
